app/__init__.py
app/__main__.py
app/filter.py
app/request.py
app/routes.py
app/version.py
app/models/__init__.py
app/models/config.py
app/models/endpoint.py
app/models/g_classes.py
app/static/build/.gitignore
app/static/css/dark-theme.css
app/static/css/dark-theme.min.css
app/static/css/dark-theme.sass
app/static/css/error.css
app/static/css/error.min.css
app/static/css/error.sass
app/static/css/header.css
app/static/css/header.min.css
app/static/css/header.sass
app/static/css/input.css
app/static/css/input.min.css
app/static/css/input.sass
app/static/css/light-theme.css
app/static/css/light-theme.min.css
app/static/css/light-theme.sass
app/static/css/logo.css
app/static/css/logo.min.css
app/static/css/logo.sass
app/static/css/main.css
app/static/css/main.min.css
app/static/css/main.sass
app/static/css/search.css
app/static/css/search.min.css
app/static/css/search.sass
app/static/css/variables.css
app/static/css/variables.min.css
app/static/css/variables.sass
app/static/img/logo.png
app/static/img/robot.png
app/static/img/setting.svg
app/static/img/whoogle.svg
app/static/img/favicon/android-chrome-192x192.png
app/static/img/favicon/android-chrome-512x512.png
app/static/img/favicon/android-icon-144x144.png
app/static/img/favicon/android-icon-192x192.png
app/static/img/favicon/android-icon-36x36.png
app/static/img/favicon/android-icon-48x48.png
app/static/img/favicon/android-icon-72x72.png
app/static/img/favicon/android-icon-96x96.png
app/static/img/favicon/apple-icon-114x114.png
app/static/img/favicon/apple-icon-120x120.png
app/static/img/favicon/apple-icon-144x144.png
app/static/img/favicon/apple-icon-152x152.png
app/static/img/favicon/apple-icon-180x180.png
app/static/img/favicon/apple-icon-57x57.png
app/static/img/favicon/apple-icon-60x60.png
app/static/img/favicon/apple-icon-72x72.png
app/static/img/favicon/apple-icon-76x76.png
app/static/img/favicon/apple-icon-precomposed.png
app/static/img/favicon/apple-icon.png
whoogle_search_kdev-0.8.2.dist-info/LICENSE
whoogle_search_kdev-0.8.2.dist-info/METADATA
whoogle_search_kdev-0.8.2.dist-info/WHEEL
whoogle_search_kdev-0.8.2.dist-info/entry_points.txt
whoogle_search_kdev-0.8.2.dist-info/top_level.txt
whoogle_search_kdev-0.8.2.dist-info/RECORD
