Metadata-Version: 2.1
Name: whoogle-search-kdev
Version: 0.8.2
Summary: Self-hosted, ad-free, privacy-respecting metasearch engine
Home-page: https://github.com/koval01/whoogle-search-kdev
Author: Ben Busby
Author-email: contact@koval01.com
License: MIT
Keywords: search,metasearch,flask,adblock,degoogle,privacy
Classifier: Programming Language :: Python :: 3
Classifier: License :: OSI Approved :: MIT License
Classifier: Operating System :: OS Independent
License-File: LICENSE
Requires-Dist: beautifulsoup4
Requires-Dist: brotli
Requires-Dist: cssutils
Requires-Dist: cryptography
Requires-Dist: defusedxml
Requires-Dist: Flask
Requires-Dist: python-dotenv
Requires-Dist: requests
Requires-Dist: stem
Requires-Dist: waitress
Provides-Extra: dev
Requires-Dist: pycodestyle ; extra == 'dev'
Provides-Extra: test
Requires-Dist: pytest ; extra == 'test'
Requires-Dist: python-dateutil ; extra == 'test'
